downie/__init__.py
downie/_version.py
downie/py.typed
downie/cli/__init__.py
downie/cli/download.py
downie/cli/main.py
downie/cli/subtitle.py
downie/config/__init__.py
downie/config/settings.py
downie/core/__init__.py
downie/core/downloader.py
downie/core/processor.py
downie/core/subtitle.py
downie/exceptions/__init__.py
downie/exceptions/errors.py
downie/logging/__init__.py
downie/logging/logger.py
downie/models/__init__.py
downie/models/config.py
downie/models/video.py
downie/utils/__init__.py
downie/utils/ffmpeg.py
downie/utils/filesystem.py
downie/utils/validation.py
downie-0.2.0.dist-info/LICENSE
downie-0.2.0.dist-info/METADATA
downie-0.2.0.dist-info/WHEEL
downie-0.2.0.dist-info/entry_points.txt
downie-0.2.0.dist-info/top_level.txt
downie-0.2.0.dist-info/RECORD
