Metadata-Version: 2.1
Name: downie
Version: 0.2.0
Summary: Advanced video and subtitle downloader
Author-email: Brett Yang <hello@brettyang.au>
License: MIT License
Project-URL: Homepage, https://github.com/where-is-brett/downie
Project-URL: Documentation, https://downie.readthedocs.io/
Project-URL: Bug Tracker, https://github.com/where-is-brett/downie/issues
Project-URL: Source Code, https://github.com/where-is-brett/downie
Keywords: video,download,youtube,subtitles,ffmpeg
Classifier: Development Status :: 4 - Beta
Classifier: Intended Audience :: End Users/Desktop
Classifier: License :: OSI Approved :: MIT License
Classifier: Programming Language :: Python :: 3
Classifier: Programming Language :: Python :: 3.8
Classifier: Programming Language :: Python :: 3.9
Classifier: Programming Language :: Python :: 3.10
Classifier: Programming Language :: Python :: 3.11
Classifier: Topic :: Multimedia :: Video
Classifier: Topic :: Internet :: WWW/HTTP :: Indexing/Search
Requires-Python: >=3.8
License-File: LICENSE
Requires-Dist: yt-dlp>=2023.11.16
Requires-Dist: ffmpeg-python>=0.2.0
Requires-Dist: pysrt>=1.1.2
Requires-Dist: webvtt-py>=0.4.6
Requires-Dist: chardet>=4.0.0
Requires-Dist: schedule>=1.1.0
Requires-Dist: tqdm>=4.65.0
Requires-Dist: requests>=2.28.0
Requires-Dist: click>=8.0.0
Requires-Dist: pyyaml>=6.0.1
Requires-Dist: colorama>=0.4.6
Requires-Dist: typing-extensions>=4.0.0
Provides-Extra: dev
Requires-Dist: black>=23.1.0; extra == "dev"
Requires-Dist: isort>=5.12.0; extra == "dev"
Requires-Dist: flake8>=6.0.0; extra == "dev"
Requires-Dist: mypy>=1.0.0; extra == "dev"
Requires-Dist: pre-commit>=3.0.0; extra == "dev"
Requires-Dist: pytest>=7.3.1; extra == "dev"
Requires-Dist: pytest-cov>=4.0.0; extra == "dev"
Requires-Dist: pytest-mock>=3.10.0; extra == "dev"
Requires-Dist: responses>=0.23.1; extra == "dev"
Provides-Extra: docs
Requires-Dist: mkdocs>=1.5.0; extra == "docs"
Requires-Dist: mkdocs-material>=9.0.0; extra == "docs"
Requires-Dist: mkdocstrings>=0.24.0; extra == "docs"
Requires-Dist: mkdocstrings-python>=1.7.0; extra == "docs"
Requires-Dist: pymdown-extensions>=10.0; extra == "docs"
